{
    "teleport_data": [
        {
            "x": "66",
            "y": "168",
            "destination_map_id": "2564",
            "destination_x": "41",
            "destination_y": "126"
        },
        {
            "x": "4",
            "y": "196",
            "destination_map_id": "2570",
            "destination_x": "129",
            "destination_y": "12"
        },
        {
            "x": "3",
            "y": "162",
            "destination_map_id": "2564",
            "destination_x": "96",
            "destination_y": "197"
        },
        {
            "x": "96",
            "y": "198",
            "destination_map_id": "2564",
            "destination_x": "3",
            "destination_y": "163"
        },
        {
            "x": "67",
            "y": "195",
            "destination_map_id": "2637",
            "destination_x": "104",
            "destination_y": "0"
        },
        {
            "x": "3",
            "y": "146",
            "destination_map_id": "2564",
            "destination_x": "21",
            "destination_y": "11"
        },
        {
            "x": "50",
            "y": "172",
            "destination_map_id": "2566",
            "destination_x": "15",
            "destination_y": "41"
        },
        {
            "x": "41",
            "y": "125",
            "destination_map_id": "2564",
            "destination_x": "66",
            "destination_y": "169"
        },
        {
            "x": "25",
            "y": "137",
            "destination_map_id": "2564",
            "destination_x": "36",
            "destination_y": "111"
        },
        {
            "x": "36",
            "y": "112",
            "destination_map_id": "2564",
            "destination_x": "25",
            "destination_y": "138"
        },
        {
            "x": "21",
            "y": "10",
            "destination_map_id": "2564",
            "destination_x": "3",
            "destination_y": "147"
        },
        {
            "x": "32",
            "y": "19",
            "destination_map_id": "2564",
            "destination_x": "14",
            "destination_y": "32"
        },
        {
            "x": "14",
            "y": "31",
            "destination_map_id": "2564",
            "destination_x": "32",
            "destination_y": "20"
        }
    ],
    "loop_type": "horizontal"
}