{
    "teleport_data": [
        {
            "x": "39",
            "y": "38",
            "destination_map_id": "2155",
            "destination_x": "83",
            "destination_y": "34"
        },
        {
            "x": "21",
            "y": "13",
            "destination_map_id": "2155",
            "destination_x": "87",
            "destination_y": "12"
        },
        {
            "x": "9",
            "y": "23",
            "destination_map_id": "2155",
            "destination_x": "77",
            "destination_y": "53"
        }
    ],
    "loop_type": "both"
}