{
    "teleport_data": [
        {
            "x": "63",
            "y": "9",
            "destination_map_id": "0698",
            "destination_x": "1",
            "destination_y": "101"
        },
        {
            "x": "0",
            "y": "101",
            "destination_map_id": "0698",
            "destination_x": "62",
            "destination_y": "9"
        },
        {
            "x": "0",
            "y": "100",
            "destination_map_id": "0698",
            "destination_x": "62",
            "destination_y": "9"
        },
        {
            "x": "0",
            "y": "102",
            "destination_map_id": "0698",
            "destination_x": "62",
            "destination_y": "9"
        },
        {
            "x": "27",
            "y": "27",
            "destination_map_id": "2764",
            "destination_x": "21",
            "destination_y": "44"
        },
        {
            "x": "5",
            "y": "5",
            "destination_map_id": "0697",
            "destination_x": "37",
            "destination_y": "13"
        },
        {
            "x": "38",
            "y": "0",
            "destination_map_id": "0699",
            "destination_x": "61",
            "destination_y": "1"
        },
        {
            "x": "37",
            "y": "0",
            "destination_map_id": "0699",
            "destination_x": "61",
            "destination_y": "1"
        },
        {
            "x": "6",
            "y": "5",
            "destination_map_id": "0697",
            "destination_x": "37",
            "destination_y": "13"
        },
        {
            "x": "32",
            "y": "45",
            "destination_map_id": "0711",
            "destination_x": "19",
            "destination_y": "24"
        },
        {
            "x": "12",
            "y": "12",
            "destination_map_id": "1272",
            "destination_x": "260",
            "destination_y": "12"
        }
    ],
    "loop_type": "none"
}